[
  {
    "nick_name": "linghuis",
    "user_name": "linghuis",
    "iam_id": "8c76f885b4d04d768dff5e41d26160ee",
    "user_id": 7256256,
    "avatar": "",
    "created_at": "2026-05-01T02:25:41.000+00:00"
  },
  {
    "nick_name": "wangzitao",
    "user_name": "wangzitao_leo",
    "iam_id": "242ef30c673c42f5a842e42e7c81f1f3",
    "user_id": 6553732,
    "avatar": "https://cdn-img.gitcode.com/fe/dc/9390f0e7d075c0371e84b437772a590e2018ffa99e821f7bdd524dc3b046e279.png?time=1762699622237",
    "created_at": "2026-04-24T01:55:03.000+00:00"
  }
]