{
  "repos": [
    {
      "name": "ops-transformer",
      "path": "cann/ops-transformer",
      "merged": 5445,
      "open": 267,
      "total": 5712
    },
    {
      "name": "ops-nn",
      "path": "cann/ops-nn",
      "merged": 4606,
      "open": 245,
      "total": 4851
    },
    {
      "name": "asc-devkit",
      "path": "cann/asc-devkit",
      "merged": 3070,
      "open": 140,
      "total": 3210
    },
    {
      "name": "pypto",
      "path": "cann/pypto",
      "merged": 3011,
      "open": 180,
      "total": 3191
    },
    {
      "name": "ops-math",
      "path": "cann/ops-math",
      "merged": 2392,
      "open": 259,
      "total": 2651
    },
    {
      "name": "runtime",
      "path": "cann/runtime",
      "merged": 2390,
      "open": 121,
      "total": 2511
    },
    {
      "name": "hcomm",
      "path": "cann/hcomm",
      "merged": 2155,
      "open": 278,
      "total": 2433
    },
    {
      "name": "ge",
      "path": "cann/ge",
      "merged": 2031,
      "open": 109,
      "total": 2140
    },
    {
      "name": "ascend-transformer-boost",
      "path": "cann/ascend-transformer-boost",
      "merged": 1476,
      "open": 6,
      "total": 1482
    },
    {
      "name": "hccl",
      "path": "cann/hccl",
      "merged": 1086,
      "open": 155,
      "total": 1241
    },
    {
      "name": "pto-isa",
      "path": "cann/pto-isa",
      "merged": 1013,
      "open": 42,
      "total": 1055
    },
    {
      "name": "ops-cv",
      "path": "cann/ops-cv",
      "merged": 795,
      "open": 19,
      "total": 814
    },
    {
      "name": "graph-autofusion",
      "path": "cann/graph-autofusion",
      "merged": 605,
      "open": 57,
      "total": 662
    },
    {
      "name": "cann-outreach",
      "path": "cann/cann-outreach",
      "merged": 418,
      "open": 222,
      "total": 640
    },
    {
      "name": "hixl",
      "path": "cann/hixl",
      "merged": 618,
      "open": 15,
      "total": 633
    },
    {
      "name": "catlass",
      "path": "cann/catlass",
      "merged": 548,
      "open": 56,
      "total": 604
    },
    {
      "name": "community",
      "path": "cann/community",
      "merged": 543,
      "open": 13,
      "total": 556
    },
    {
      "name": "opbase",
      "path": "cann/opbase",
      "merged": 431,
      "open": 51,
      "total": 482
    },
    {
      "name": "cann-recipes-infer",
      "path": "cann/cann-recipes-infer",
      "merged": 403,
      "open": 61,
      "total": 464
    },
    {
      "name": "shmem",
      "path": "cann/shmem",
      "merged": 420,
      "open": 43,
      "total": 463
    },
    {
      "name": "cannbot-skills",
      "path": "cann/cannbot-skills",
      "merged": 324,
      "open": 93,
      "total": 417
    },
    {
      "name": "cann-ops-competitions",
      "path": "cann/cann-ops-competitions",
      "merged": 327,
      "open": 78,
      "total": 405
    },
    {
      "name": "oam-tools",
      "path": "cann/oam-tools",
      "merged": 311,
      "open": 32,
      "total": 343
    },
    {
      "name": "pypto-gym",
      "path": "cann/pypto-gym",
      "merged": 299,
      "open": 35,
      "total": 334
    },
    {
      "name": "torchtitan-npu",
      "path": "cann/torchtitan-npu",
      "merged": 311,
      "open": 21,
      "total": 332
    },
    {
      "name": "metadef",
      "path": "cann/metadef",
      "merged": 273,
      "open": 20,
      "total": 293
    },
    {
      "name": "asc-tools",
      "path": "cann/asc-tools",
      "merged": 252,
      "open": 14,
      "total": 266
    },
    {
      "name": "cann-samples",
      "path": "cann/cann-samples",
      "merged": 214,
      "open": 12,
      "total": 226
    },
    {
      "name": "cann-learning-hub",
      "path": "cann/cann-learning-hub",
      "merged": 173,
      "open": 52,
      "total": 225
    },
    {
      "name": "ascend-boost-comm",
      "path": "cann/ascend-boost-comm",
      "merged": 208,
      "open": 8,
      "total": 216
    },
    {
      "name": "ops-blas",
      "path": "cann/ops-blas",
      "merged": 205,
      "open": 10,
      "total": 215
    },
    {
      "name": "cann-launch-camp",
      "path": "cann/cann-launch-camp",
      "merged": 157,
      "open": 44,
      "total": 201
    },
    {
      "name": "cmake",
      "path": "cann/cmake",
      "merged": 161,
      "open": 15,
      "total": 176
    },
    {
      "name": "amct",
      "path": "cann/amct",
      "merged": 153,
      "open": 11,
      "total": 164
    },
    {
      "name": "cann-bench",
      "path": "cann/cann-bench",
      "merged": 146,
      "open": 3,
      "total": 149
    },
    {
      "name": "release-management",
      "path": "cann/release-management",
      "merged": 121,
      "open": 2,
      "total": 123
    },
    {
      "name": "asnumpy",
      "path": "cann/asnumpy",
      "merged": 104,
      "open": 14,
      "total": 118
    },
    {
      "name": "cann-recipes-train",
      "path": "cann/cann-recipes-train",
      "merged": 107,
      "open": 7,
      "total": 114
    },
    {
      "name": "pyasc",
      "path": "cann/pyasc",
      "merged": 107,
      "open": 7,
      "total": 114
    },
    {
      "name": "ops-tensor",
      "path": "cann/ops-tensor",
      "merged": 93,
      "open": 16,
      "total": 109
    },
    {
      "name": "sip",
      "path": "cann/sip",
      "merged": 77,
      "open": 3,
      "total": 80
    },
    {
      "name": "cann-recipes-embodied-ai",
      "path": "cann/cann-recipes-embodied-ai",
      "merged": 68,
      "open": 10,
      "total": 78
    },
    {
      "name": "driver",
      "path": "cann/driver",
      "merged": 68,
      "open": 9,
      "total": 77
    },
    {
      "name": "catccos",
      "path": "cann/catccos",
      "merged": 59,
      "open": 16,
      "total": 75
    },
    {
      "name": "infrastructure",
      "path": "cann/infrastructure",
      "merged": 67,
      "open": 7,
      "total": 74
    },
    {
      "name": "cann-recipes-harmony-infer",
      "path": "cann/cann-recipes-harmony-infer",
      "merged": 45,
      "open": 1,
      "total": 46
    },
    {
      "name": "ops-sparse",
      "path": "cann/ops-sparse",
      "merged": 39,
      "open": 5,
      "total": 44
    },
    {
      "name": "atvoss",
      "path": "cann/atvoss",
      "merged": 37,
      "open": 5,
      "total": 42
    },
    {
      "name": "ops-rand",
      "path": "cann/ops-rand",
      "merged": 33,
      "open": 1,
      "total": 34
    },
    {
      "name": "cann-recipes-spatial-intelligence",
      "path": "cann/cann-recipes-spatial-intelligence",
      "merged": 29,
      "open": 3,
      "total": 32
    },
    {
      "name": "elec-ops-inspection",
      "path": "cann/elec-ops-inspection",
      "merged": 29,
      "open": 3,
      "total": 32
    },
    {
      "name": "atvc",
      "path": "cann/atvc",
      "merged": 20,
      "open": 4,
      "total": 24
    },
    {
      "name": "ops-collections",
      "path": "cann/ops-collections",
      "merged": 22,
      "open": 1,
      "total": 23
    },
    {
      "name": "ops-fft",
      "path": "cann/ops-fft",
      "merged": 19,
      "open": 4,
      "total": 23
    },
    {
      "name": "ops-test-kit",
      "path": "cann/ops-test-kit",
      "merged": 17,
      "open": 5,
      "total": 22
    },
    {
      "name": "mat-chem-sim-pred",
      "path": "cann/mat-chem-sim-pred",
      "merged": 19,
      "open": 2,
      "total": 21
    },
    {
      "name": "ops-solver",
      "path": "cann/ops-solver",
      "merged": 16,
      "open": 3,
      "total": 19
    },
    {
      "name": "ops-multimodal-fusion",
      "path": "cann/ops-multimodal-fusion",
      "merged": 14,
      "open": 3,
      "total": 17
    },
    {
      "name": "tensorflow",
      "path": "cann/tensorflow",
      "merged": 14,
      "open": 3,
      "total": 17
    },
    {
      "name": "cann-spack-package",
      "path": "cann/cann-spack-package",
      "merged": 11,
      "open": 5,
      "total": 16
    },
    {
      "name": "docs",
      "path": "cann/docs",
      "merged": 16,
      "open": 0,
      "total": 16
    },
    {
      "name": "manifest",
      "path": "cann/manifest",
      "merged": 12,
      "open": 2,
      "total": 14
    },
    {
      "name": "triton-inference-server-ge-backend",
      "path": "cann/triton-inference-server-ge-backend",
      "merged": 12,
      "open": 0,
      "total": 12
    },
    {
      "name": "xla-npu",
      "path": "cann/xla-npu",
      "merged": 8,
      "open": 1,
      "total": 9
    },
    {
      "name": ".gitcode",
      "path": "cann/.gitcode",
      "merged": 8,
      "open": 0,
      "total": 8
    },
    {
      "name": "elec-ops-prediction",
      "path": "cann/elec-ops-prediction",
      "merged": 5,
      "open": 3,
      "total": 8
    },
    {
      "name": "elec-ops-simulation",
      "path": "cann/elec-ops-simulation",
      "merged": 5,
      "open": 2,
      "total": 7
    },
    {
      "name": "asnumpy-docs",
      "path": "cann/asnumpy-docs",
      "merged": 5,
      "open": 0,
      "total": 5
    }
  ],
  "unique_authors": 3791,
  "generated_at": "2026-07-10"
}