{
  "repos": [
    {
      "name": "ops-transformer",
      "path": "cann/ops-transformer",
      "merged": 3745,
      "open": 267,
      "total": 4012
    },
    {
      "name": "ops-nn",
      "path": "cann/ops-nn",
      "merged": 3309,
      "open": 323,
      "total": 3632
    },
    {
      "name": "pypto",
      "path": "cann/pypto",
      "merged": 2120,
      "open": 163,
      "total": 2283
    },
    {
      "name": "ops-math",
      "path": "cann/ops-math",
      "merged": 1761,
      "open": 182,
      "total": 1943
    },
    {
      "name": "asc-devkit",
      "path": "cann/asc-devkit",
      "merged": 1747,
      "open": 176,
      "total": 1923
    },
    {
      "name": "ge",
      "path": "cann/ge",
      "merged": 1539,
      "open": 163,
      "total": 1702
    },
    {
      "name": "runtime",
      "path": "cann/runtime",
      "merged": 1575,
      "open": 116,
      "total": 1691
    },
    {
      "name": "hcomm",
      "path": "cann/hcomm",
      "merged": 1467,
      "open": 160,
      "total": 1627
    },
    {
      "name": "ascend-transformer-boost",
      "path": "cann/ascend-transformer-boost",
      "merged": 1435,
      "open": 15,
      "total": 1450
    },
    {
      "name": "pto-isa",
      "path": "cann/pto-isa",
      "merged": 778,
      "open": 29,
      "total": 807
    },
    {
      "name": "hccl",
      "path": "cann/hccl",
      "merged": 568,
      "open": 101,
      "total": 669
    },
    {
      "name": "ops-cv",
      "path": "cann/ops-cv",
      "merged": 641,
      "open": 20,
      "total": 661
    },
    {
      "name": "community",
      "path": "cann/community",
      "merged": 450,
      "open": 6,
      "total": 456
    },
    {
      "name": "hixl",
      "path": "cann/hixl",
      "merged": 427,
      "open": 25,
      "total": 452
    },
    {
      "name": "catlass",
      "path": "cann/catlass",
      "merged": 394,
      "open": 35,
      "total": 429
    },
    {
      "name": "graph-autofusion",
      "path": "cann/graph-autofusion",
      "merged": 343,
      "open": 37,
      "total": 380
    },
    {
      "name": "cann-recipes-infer",
      "path": "cann/cann-recipes-infer",
      "merged": 292,
      "open": 41,
      "total": 333
    },
    {
      "name": "opbase",
      "path": "cann/opbase",
      "merged": 295,
      "open": 30,
      "total": 325
    },
    {
      "name": "shmem",
      "path": "cann/shmem",
      "merged": 272,
      "open": 35,
      "total": 307
    },
    {
      "name": "asc-tools",
      "path": "cann/asc-tools",
      "merged": 215,
      "open": 18,
      "total": 233
    },
    {
      "name": "metadef",
      "path": "cann/metadef",
      "merged": 215,
      "open": 18,
      "total": 233
    },
    {
      "name": "oam-tools",
      "path": "cann/oam-tools",
      "merged": 195,
      "open": 25,
      "total": 220
    },
    {
      "name": "ascend-boost-comm",
      "path": "cann/ascend-boost-comm",
      "merged": 206,
      "open": 9,
      "total": 215
    },
    {
      "name": "cannbot-skills",
      "path": "cann/cannbot-skills",
      "merged": 160,
      "open": 47,
      "total": 207
    },
    {
      "name": "torchtitan-npu",
      "path": "cann/torchtitan-npu",
      "merged": 177,
      "open": 26,
      "total": 203
    },
    {
      "name": "cann-samples",
      "path": "cann/cann-samples",
      "merged": 174,
      "open": 15,
      "total": 189
    },
    {
      "name": "asnumpy",
      "path": "cann/asnumpy",
      "merged": 101,
      "open": 13,
      "total": 114
    },
    {
      "name": "cann-competitions",
      "path": "cann/cann-competitions",
      "merged": 87,
      "open": 26,
      "total": 113
    },
    {
      "name": "pyasc",
      "path": "cann/pyasc",
      "merged": 97,
      "open": 11,
      "total": 108
    },
    {
      "name": "cmake",
      "path": "cann/cmake",
      "merged": 89,
      "open": 16,
      "total": 105
    },
    {
      "name": "amct",
      "path": "cann/amct",
      "merged": 94,
      "open": 9,
      "total": 103
    },
    {
      "name": "cann-recipes-train",
      "path": "cann/cann-recipes-train",
      "merged": 95,
      "open": 3,
      "total": 98
    },
    {
      "name": "release-management",
      "path": "cann/release-management",
      "merged": 93,
      "open": 0,
      "total": 93
    },
    {
      "name": "cann-outreach",
      "path": "cann/cann-outreach",
      "merged": 52,
      "open": 36,
      "total": 88
    },
    {
      "name": "cann-learning-hub",
      "path": "cann/cann-learning-hub",
      "merged": 61,
      "open": 20,
      "total": 81
    },
    {
      "name": "cann-recipes-embodied-ai",
      "path": "cann/cann-recipes-embodied-ai",
      "merged": 60,
      "open": 5,
      "total": 65
    },
    {
      "name": "ops-blas",
      "path": "cann/ops-blas",
      "merged": 50,
      "open": 14,
      "total": 64
    },
    {
      "name": "sip",
      "path": "cann/sip",
      "merged": 62,
      "open": 1,
      "total": 63
    },
    {
      "name": "infrastructure",
      "path": "cann/infrastructure",
      "merged": 56,
      "open": 3,
      "total": 59
    },
    {
      "name": "cann-bench",
      "path": "cann/cann-bench",
      "merged": 52,
      "open": 4,
      "total": 56
    },
    {
      "name": "ops-tensor",
      "path": "cann/ops-tensor",
      "merged": 47,
      "open": 8,
      "total": 55
    },
    {
      "name": "driver",
      "path": "cann/driver",
      "merged": 47,
      "open": 5,
      "total": 52
    },
    {
      "name": "atvoss",
      "path": "cann/atvoss",
      "merged": 35,
      "open": 4,
      "total": 39
    },
    {
      "name": "cann-recipes-harmony-infer",
      "path": "cann/cann-recipes-harmony-infer",
      "merged": 38,
      "open": 1,
      "total": 39
    },
    {
      "name": "catccos",
      "path": "cann/catccos",
      "merged": 23,
      "open": 15,
      "total": 38
    },
    {
      "name": "ops-rand",
      "path": "cann/ops-rand",
      "merged": 33,
      "open": 1,
      "total": 34
    },
    {
      "name": "cann-recipes-spatial-intelligence",
      "path": "cann/cann-recipes-spatial-intelligence",
      "merged": 29,
      "open": 3,
      "total": 32
    },
    {
      "name": "atvc",
      "path": "cann/atvc",
      "merged": 19,
      "open": 4,
      "total": 23
    },
    {
      "name": "ops-fft",
      "path": "cann/ops-fft",
      "merged": 17,
      "open": 2,
      "total": 19
    },
    {
      "name": "ops-collections",
      "path": "cann/ops-collections",
      "merged": 15,
      "open": 1,
      "total": 16
    },
    {
      "name": "ops-solver",
      "path": "cann/ops-solver",
      "merged": 13,
      "open": 1,
      "total": 14
    },
    {
      "name": "tensorflow",
      "path": "cann/tensorflow",
      "merged": 7,
      "open": 7,
      "total": 14
    },
    {
      "name": "cann-spack-package",
      "path": "cann/cann-spack-package",
      "merged": 9,
      "open": 4,
      "total": 13
    },
    {
      "name": "mat-chem-sim-pred",
      "path": "cann/mat-chem-sim-pred",
      "merged": 11,
      "open": 2,
      "total": 13
    },
    {
      "name": "ops-sparse",
      "path": "cann/ops-sparse",
      "merged": 9,
      "open": 2,
      "total": 11
    },
    {
      "name": "triton-inference-server-ge-backend",
      "path": "cann/triton-inference-server-ge-backend",
      "merged": 11,
      "open": 0,
      "total": 11
    },
    {
      "name": "manifest",
      "path": "cann/manifest",
      "merged": 9,
      "open": 1,
      "total": 10
    },
    {
      "name": "elec-ops-inspection",
      "path": "cann/elec-ops-inspection",
      "merged": 6,
      "open": 3,
      "total": 9
    },
    {
      "name": "elec-ops-prediction",
      "path": "cann/elec-ops-prediction",
      "merged": 5,
      "open": 3,
      "total": 8
    },
    {
      "name": "ops-test-kit",
      "path": "cann/ops-test-kit",
      "merged": 6,
      "open": 2,
      "total": 8
    },
    {
      "name": "elec-ops-simulation",
      "path": "cann/elec-ops-simulation",
      "merged": 5,
      "open": 2,
      "total": 7
    },
    {
      "name": "xla-npu",
      "path": "cann/xla-npu",
      "merged": 6,
      "open": 0,
      "total": 6
    },
    {
      "name": "asnumpy-docs",
      "path": "cann/asnumpy-docs",
      "merged": 5,
      "open": 0,
      "total": 5
    },
    {
      "name": ".gitcode",
      "path": "cann/.gitcode",
      "merged": 2,
      "open": 0,
      "total": 2
    }
  ],
  "unique_authors": 2556,
  "generated_at": "2026-05-26"
}