[
  {
    "iid": 12,
    "state": "opened",
    "created_at": "2026-06-26",
    "closed_at": "",
    "author": "zhangzhizhuo"
  },
  {
    "iid": 11,
    "state": "opened",
    "created_at": "2026-06-25",
    "closed_at": "",
    "author": "dai-zhentao"
  },
  {
    "iid": 10,
    "state": "closed",
    "created_at": "2026-06-23",
    "closed_at": "2026-06-26",
    "author": "LINxu233"
  },
  {
    "iid": 9,
    "state": "opened",
    "created_at": "2026-06-18",
    "closed_at": "",
    "author": "yiqiao-wjp"
  },
  {
    "iid": 8,
    "state": "opened",
    "created_at": "2026-06-11",
    "closed_at": "",
    "author": "ayistar"
  },
  {
    "iid": 7,
    "state": "opened",
    "created_at": "2026-06-10",
    "closed_at": "",
    "author": "LINxu233"
  },
  {
    "iid": 6,
    "state": "closed",
    "created_at": "2026-06-10",
    "closed_at": "2026-06-10",
    "author": "chenkang30"
  },
  {
    "iid": 5,
    "state": "opened",
    "created_at": "2026-06-10",
    "closed_at": "",
    "author": "luobaiqing"
  },
  {
    "iid": 4,
    "state": "closed",
    "created_at": "2026-06-10",
    "closed_at": "2026-06-15",
    "author": "smdbha"
  },
  {
    "iid": 3,
    "state": "closed",
    "created_at": "2026-06-05",
    "closed_at": "2026-06-05",
    "author": "chenkang30"
  },
  {
    "iid": 2,
    "state": "closed",
    "created_at": "2026-06-03",
    "closed_at": "2026-06-04",
    "author": "Hu1L1"
  },
  {
    "iid": 1,
    "state": "closed",
    "created_at": "2026-03-25",
    "closed_at": "2026-03-25",
    "author": "liuyufan0725"
  }
]